setup.py
socketome/__init__.py
socketome/protocols.py
socketome.egg-info/PKG-INFO
socketome.egg-info/SOURCES.txt
socketome.egg-info/dependency_links.txt
socketome.egg-info/top_level.txt
