Metadata-Version: 1.0
Name: socketome
Version: 0.03
Summary: A non blocking TCP networking core based on select.
Home-page: http://exactlysimilar.org/docs/socketome
Author: Simon Wittber
Author-email: simonwittber@gmail.com
License: MIT
Platform: Any
